Metadata-Version: 2.1
Name: PyMySQLPlus
Version: 1.0.2
Summary: Fix bug base on Pure Python MySQL Driver and Inception
Home-page: https://github.com/PyMySQL/PyMySQL/
Author: yutaka.matsubara
Author-email: yutaka.matsubara@gmail.com
Maintainer: Inada Naoki
Maintainer-email: songofacandy@gmail.com
License: "MIT"
Project-URL: Documentation, https://pymysql.readthedocs.io/
Keywords: MySQL
Platform: UNKNOWN
Classifier: Development Status :: 5 - Production/Stable
Classifier: Programming Language :: Python :: 3
Classifier: Programming Language :: Python :: 3.6
Classifier: Programming Language :: Python :: 3.7
Classifier: Programming Language :: Python :: 3.8
Classifier: Programming Language :: Python :: 3.9
Classifier: Programming Language :: Python :: Implementation :: CPython
Classifier: Programming Language :: Python :: Implementation :: PyPy
Classifier: Intended Audience :: Developers
Classifier: License :: OSI Approved :: MIT License
Classifier: Topic :: Database
Requires-Python: >=3.6
Provides-Extra: ed25519
Requires-Dist: PyNaCl (>=1.4.0) ; extra == 'ed25519'
Provides-Extra: rsa
Requires-Dist: cryptography ; extra == 'rsa'
